LICENSE
MANIFEST.in
README.md
setup.py
binding/__init__.py
binding/apps.py
binding/binding.py
binding/dnw.py
binding/drf.py
binding/listeners.py
binding/models.py
binding/tasks.py
binding/management/__init__.py
binding/management/commands/__init__.py
binding/management/commands/bindingbump.py
binding/management/commands/bindingclear.py
binding/management/commands/bindinglist.py
binding/management/commands/bindingsync.py
binding/tests/__init__.py
binding/tests/_binding.py
binding/tests/test_binding.py
binding/tests/test_dnw.py
binding/tests/test_drf.py
binding_test/__init__.py
binding_test/models.py
django_binding.egg-info/PKG-INFO
django_binding.egg-info/SOURCES.txt
django_binding.egg-info/dependency_links.txt
django_binding.egg-info/pbr.json
django_binding.egg-info/top_level.txt