Metadata-Version: 1.0
Name: django-binding
Version: 0.7.4
Summary: Django data binding backend
Home-page: UNKNOWN
Author: John Leith
Author-email: dev@velocitywebworks.com
License: UNKNOWN
Platform: UNKNOWN
